font_configurator/__init__.py
font_configurator/font_configurator.py
font_configurator/fontconfig_managers.py
font_configurator/fontconfig_templates.py
font_download/__init__.py
font_download/config.py
font_download/download_fonts.py
font_download/fonts.py
font_download/example_fonts/__init__.py
font_download/example_fonts/honk.py
font_download/example_fonts/noto_sans.py
pixel_renderer/__init__.py
pixel_renderer/processor.py
pixel_renderer/renderer.py
pixel_renderer-0.1.2.dist-info/licenses/LICENSE
pixel_renderer-0.1.2.dist-info/METADATA
pixel_renderer-0.1.2.dist-info/WHEEL
pixel_renderer-0.1.2.dist-info/top_level.txt
pixel_renderer-0.1.2.dist-info/RECORD
