Metadata-Version: 2.4
Name: pixel-renderer
Version: 0.1.2
Summary: Text renderer for PIXEL models
Author-email: Ilker Kesen <ilkerksn@gmail.com>, Amit Moryossef <amit@sign.mt>
Requires-Python: >=3.10
License-File: LICENSE
Requires-Dist: numpy
Requires-Dist: Pillow
Requires-Dist: utf8-tokenizer
Requires-Dist: lxml
Requires-Dist: requests
Requires-Dist: signwriting
Requires-Dist: platformdirs
Requires-Dist: torchvision
Provides-Extra: dev
Requires-Dist: ruff; extra == "dev"
Requires-Dist: pytest; extra == "dev"
Requires-Dist: pytest-xdist; extra == "dev"
Provides-Extra: pangocairo
Requires-Dist: pycairo; extra == "pangocairo"
Requires-Dist: PyGObject<3.52; extra == "pangocairo"
Dynamic: license-file
